ally_ai/__init__.py
ally_ai/chroma/__init__.py
ally_ai/core/__init__.py
ally_ai/langchain/__init__.py
ally_ai-0.2.0.dist-info/LICENSE
ally_ai-0.2.0.dist-info/METADATA
ally_ai-0.2.0.dist-info/WHEEL
ally_ai-0.2.0.dist-info/top_level.txt
ally_ai-0.2.0.dist-info/RECORD
